<annotation>
  <folder>tulip</folder>
  <filename>13888320717_d2919a879b_m</filename>
  <path>C:\Users\user\Anacondaa3\envs\tensorflow_cpu\TensorFlow\workspace\training_demo\Images\flowers\tulip\13888320717_d2919a879b_m.jpg</path>
  <source>
    <database>Unknown</database>
  </source>
  <size>
    <width>159</width>
    <height>240</height>
    <depth>3</depth>
  </size>
  <segmented>0</segmented>
  <object>
    <name>Tulip</name>
    <pose>Unspecified</pose>
    <truncated>0</truncated>
    <difficult>0</difficult>
    <bndbox>
      <xmin>1</xmin>
      <ymin>1</ymin>
      <xmax>156</xmax>
      <ymax>237</ymax>
    </bndbox>
  </object>
</annotation>
