<annotation>
  <folder>dandelion</folder>
  <filename>14012247974_69ac128799</filename>
  <path>C:\Users\user\Anacondaa3\envs\tensorflow_cpu\TensorFlow\workspace\training_demo\Images\flowers\dandelion\14012247974_69ac128799.jpg</path>
  <source>
    <database>Unknown</database>
  </source>
  <size>
    <width>500</width>
    <height>281</height>
    <depth>3</depth>
  </size>
  <segmented>0</segmented>
  <object>
    <name>Dandelion</name>
    <pose>Unspecified</pose>
    <truncated>0</truncated>
    <difficult>0</difficult>
    <bndbox>
      <xmin>1</xmin>
      <ymin>1</ymin>
      <xmax>423</xmax>
      <ymax>281</ymax>
    </bndbox>
  </object>
</annotation>
