<annotation>
  <folder>Hibiscus</folder>
  <filename>312618ec550675aa6b47efbac6aa3993--blue-hibiscus-hibiscus-flowers</filename>
  <path>C:\Users\user\Anacondaa3\envs\tensorflow_cpu\TensorFlow\workspace\training_demo\Images\flowers\Hibiscus\312618ec550675aa6b47efbac6aa3993--blue-hibiscus-hibiscus-flowers.jpg</path>
  <source>
    <database>Unknown</database>
  </source>
  <size>
    <width>236</width>
    <height>236</height>
    <depth>3</depth>
  </size>
  <segmented>0</segmented>
  <object>
    <name>Hibiscus</name>
    <pose>Unspecified</pose>
    <truncated>0</truncated>
    <difficult>0</difficult>
    <bndbox>
      <xmin>18</xmin>
      <ymin>42</ymin>
      <xmax>195</xmax>
      <ymax>222</ymax>
    </bndbox>
  </object>
  <object>
    <name>Hibiscus</name>
    <pose>Unspecified</pose>
    <truncated>0</truncated>
    <difficult>0</difficult>
    <bndbox>
      <xmin>6</xmin>
      <ymin>12</ymin>
      <xmax>75</xmax>
      <ymax>54</ymax>
    </bndbox>
  </object>
  <object>
    <name>Hibiscus</name>
    <pose>Unspecified</pose>
    <truncated>0</truncated>
    <difficult>0</difficult>
    <bndbox>
      <xmin>98</xmin>
      <ymin>2</ymin>
      <xmax>128</xmax>
      <ymax>35</ymax>
    </bndbox>
  </object>
  <object>
    <name>Hibiscus</name>
    <pose>Unspecified</pose>
    <truncated>0</truncated>
    <difficult>0</difficult>
    <bndbox>
      <xmin>141</xmin>
      <ymin>26</ymin>
      <xmax>184</xmax>
      <ymax>54</ymax>
    </bndbox>
  </object>
</annotation>
