<annotation>
  <folder>Hibiscus</folder>
  <filename>7410a1feaa7c8c8333e71dbfcf8ecec7--hibiscus-flowers-art-flowers0</filename>
  <path>C:\Users\user\Anacondaa3\envs\tensorflow_cpu\TensorFlow\workspace\training_demo\Images\flowers\Hibiscus\7410a1feaa7c8c8333e71dbfcf8ecec7--hibiscus-flowers-art-flowers0.jpg</path>
  <source>
    <database>Unknown</database>
  </source>
  <size>
    <width>247</width>
    <height>300</height>
    <depth>3</depth>
  </size>
  <segmented>0</segmented>
  <object>
    <name>Hibiscus</name>
    <pose>Unspecified</pose>
    <truncated>0</truncated>
    <difficult>0</difficult>
    <bndbox>
      <xmin>17</xmin>
      <ymin>27</ymin>
      <xmax>226</xmax>
      <ymax>278</ymax>
    </bndbox>
  </object>
</annotation>
